{"name":"Samuel Reed","tagline":"CTO of BitMEX.com, NodeJS & Javascript Enthusiast","body":"### Recent Projects.\r\n\r\n[Securesha.re](http://securesha.re)\r\n\r\n![Securesha.re](images/secureshare.png)\r\n\r\n```javascript\r\n...\r\nvar fileReader = new FileReaderSync();\r\nvar fileData = fileReader.readAsBinaryString(oEvent.data.file);\r\n\r\nvar encrypted = {};\r\nencrypted.fileData = CryptoJS.Rabbit.encrypt(fileData, oEvent.data.passphrase).toString();\r\nencrypted.fileName = CryptoJS.Rabbit.encrypt(oEvent.data.file.name, oEvent.data.passphrase).toString();\r\npostMessage(encrypted);\r\n...\r\n```\r\n\r\n[Tixelated](www.tixelated.com)\r\n\r\n![Tixelated](images/tixelated.png)\r\n\r\n[Mongoose-Filter-Denormalize](https://github.com/STRML/mongoose-filter-denormalize)\r\n\r\n```javascript\r\nUserSchema.plugin(filter, {\r\n  readFilter: {\r\n      \"owner\" : ['name', 'address', 'fb.id', 'fb.name', 'readOnlyField'],\r\n      \"public\": ['name', 'fb.name']\r\n  },\r\n  writeFilter: {\r\n      \"owner\" : ['name', 'address', 'fb.id', 'writeOnlyField']\r\n  },\r\n  defaultFilterRole: 'public',\r\n  sanitize: true // Escape HTML in strings\r\n});\r\n\r\nUserSchema.plugin(denormalize, {defaults: ['address', 'transactions', 'tickets'], exclude: 'bankaccount'});\r\n```\r\n\r\n[jQuery.scrollingShadows](https://github.com/STRML/jquery.scrollingShadows)\r\n\r\n[Demo](strml.github.com/examples/jquery.scrollingShadows.html)\r\n\r\n```javascript\r\n$(\"#viewport\").scrollingShadows(\".longTextBox\");\r\n```","google":"","note":"Don't delete this file! It's used internally to help with page regeneration."}